_pglib.cpython-38-darwin.so
pglib/__init__.py
pglib/_version.py
pglib/asyncpglib.py
pglib-5.2.0.dist-info/LICENSE
pglib-5.2.0.dist-info/METADATA
pglib-5.2.0.dist-info/WHEEL
pglib-5.2.0.dist-info/top_level.txt
pglib-5.2.0.dist-info/RECORD
