Metadata-Version: 2.1
Name: pglib
Version: 5.2.0
Summary: A PostgreSQL interface
Home-page: https://gitlab.com/mkleehammer/pglib
Maintainer: Michael Kleehammer
Maintainer-email: michael@kleehammer.com
License: MIT
Keywords: postgresql postgres
Platform: UNKNOWN
Classifier: Development Status :: 5 - Production/Stable
Classifier: Intended Audience :: Developers
Classifier: Topic :: Database
Classifier: License :: OSI Approved :: MIT License
Classifier: Programming Language :: Python :: 3
Classifier: Programming Language :: Python :: 3 :: Only
